LICENSE.txt
README.rst
setup.py
captcha_rest_validator.egg-info/PKG-INFO
captcha_rest_validator.egg-info/SOURCES.txt
captcha_rest_validator.egg-info/dependency_links.txt
captcha_rest_validator.egg-info/requires.txt
captcha_rest_validator.egg-info/top_level.txt
rest_validator/__init__.py
rest_validator/apps.py
rest_validator/fields.py
rest_validator/serializers.py
rest_validator/urls.py
rest_validator/views.py
rest_validator/conf/__init__.py
rest_validator/conf/settings.py
rest_validator/migrations/__init__.py
tests/__init__.py
tests/models.py
tests/serializers.py
tests/test_settings.py
tests/tests.py
tests/urls.py
tests/views.py